hvvabfahrtsmonitor/__init__.py
hvvabfahrtsmonitor/hvvabfahrtsmonitor.py
hvvabfahrtsmonitor-0.1.1.dist-info/LICENSE
hvvabfahrtsmonitor-0.1.1.dist-info/METADATA
hvvabfahrtsmonitor-0.1.1.dist-info/WHEEL
hvvabfahrtsmonitor-0.1.1.dist-info/top_level.txt
hvvabfahrtsmonitor-0.1.1.dist-info/RECORD
