Metadata-Version: 2.1
Name: hvvabfahrtsmonitor
Version: 0.1.1
Summary: Do requests to the hvv abfahrtsmonitor and get parsed data
Home-page: https://github.com/mcantureinhard/hvvabfahrtsmonitor
Author: Manuel Catu
Author-email: m.cantu.reinhard@gmail.com
License: UNKNOWN
Platform: UNKNOWN
Classifier: Programming Language :: Python :: 3
Classifier: License :: OSI Approved :: MIT License
Classifier: Operating System :: OS Independent
